radam/RAdam.py
radam/__init__.py
tf_1.x_rectified_adam-0.0.2.dist-info/LICENSE
tf_1.x_rectified_adam-0.0.2.dist-info/METADATA
tf_1.x_rectified_adam-0.0.2.dist-info/WHEEL
tf_1.x_rectified_adam-0.0.2.dist-info/top_level.txt
tf_1.x_rectified_adam-0.0.2.dist-info/RECORD
