Metadata-Version: 2.1
Name: tf-1.x-rectified-adam
Version: 0.0.2
Summary: RAdam implemented in Tensorflow 1.x
Home-page: https://github.com/satyenrajpal/RAdam-Tensorflow
Author: Satyen Rajpal
Author-email: satyen.2.rajpal@gmail.com
License: MIT
Platform: UNKNOWN
Classifier: Programming Language :: Python :: 3.6
Classifier: License :: OSI Approved :: MIT License
Classifier: Operating System :: OS Independent
Requires-Dist: tensorflow (==1.15.0.1)
